[{"model": "api_development.machine", "pk": 3, "fields": {"name": "HkkBgtMainDetection-1", "related_directory": "HkkBgtMainDetection-1", "valid_file_count": 18, "last_scanned": "2024-05-22T01:36:03.845Z"}}, {"model": "api_development.machine", "pk": 4, "fields": {"name": "HkkBgtMainDetection-2​", "related_directory": "HkkBgtMainDetection-2", "valid_file_count": 18, "last_scanned": "2024-05-22T01:36:32.403Z"}}, {"model": "api_development.machine", "pk": 5, "fields": {"name": "HkkBctDetection-1", "related_directory": "HkkBctDetection-1", "valid_file_count": 18, "last_scanned": "2024-05-22T01:36:32.409Z"}}, {"model": "api_development.machine", "pk": 6, "fields": {"name": "HkkBctDetection-2​", "related_directory": "HkkBctDetection-2​", "valid_file_count": 18, "last_scanned": "2024-05-22T01:36:32.413Z"}}, {"model": "api_development.machine", "pk": 7, "fields": {"name": "HkkBctDetection-3", "related_directory": "HkkBctDetection-3", "valid_file_count": 18, "last_scanned": "2024-05-22T01:36:32.418Z"}}]